goodconf/__init__.py
goodconf/_version.py
goodconf/py.typed
goodconf/contrib/__init__.py
goodconf/contrib/argparse.py
goodconf/contrib/django.py
goodconf-6.1.2.dist-info/METADATA
goodconf-6.1.2.dist-info/WHEEL
goodconf-6.1.2.dist-info/licenses/LICENSE
goodconf-6.1.2.dist-info/RECORD
