Metadata-Version: 2.4
Name: goodconf
Version: 6.1.2
Summary: Load configuration variables from a file or environment
Project-URL: homepage, https://github.com/lincolnloop/goodconf/
Project-URL: changelog, https://github.com/lincolnloop/goodconf/blob/main/CHANGES.rst
Author-email: Peter Baumgartner <brett@python.org>
License: Copyright (c) 2018 Lincoln Loop
License-File: LICENSE
Keywords: config,env,json,toml,yaml
Classifier: Development Status :: 5 - Production/Stable
Classifier: Intended Audience :: Developers
Classifier: License :: OSI Approved :: MIT License
Classifier: Operating System :: OS Independent
Classifier: Programming Language :: Python
Classifier: Programming Language :: Python :: 3.9
Classifier: Programming Language :: Python :: 3.10
Classifier: Programming Language :: Python :: 3.11
Classifier: Programming Language :: Python :: 3.12
Requires-Python: >=3.9
Requires-Dist: pydantic-settings>=2.4
Requires-Dist: pydantic>=2.7
Provides-Extra: tests
Requires-Dist: django>=3.2.0; extra == 'tests'
Requires-Dist: pytest-cov==4.0.*; extra == 'tests'
Requires-Dist: pytest-mock==3.10.*; extra == 'tests'
Requires-Dist: pytest==7.2.*; extra == 'tests'
Requires-Dist: ruamel-yaml>=0.17.0; extra == 'tests'
Requires-Dist: tomlkit>=0.11.6; extra == 'tests'
Provides-Extra: toml
Requires-Dist: tomlkit>=0.11.6; extra == 'toml'
Provides-Extra: yaml
Requires-Dist: ruamel-yaml>=0.17.0; extra == 'yaml'
